simple_terminal_control/__init__.py
simple_terminal_control/_raw_keys.py
simple_terminal_control/keys.py
simple_terminal_control/position.py
simple_terminal_control/py.typed
simple_terminal_control/util/__init__.py
simple_terminal_control/util/debug.py
simple_terminal_control/util/terminal.py
simple_terminal_control-0.1.2.dist-info/METADATA
simple_terminal_control-0.1.2.dist-info/WHEEL
simple_terminal_control-0.1.2.dist-info/licenses/LICENSE
simple_terminal_control-0.1.2.dist-info/RECORD
