Metadata-Version: 2.1
Name: simple-terminal-control
Version: 0.1.2
Summary: Higher level control for the terminal
Project-URL: Homepage, https://github.com/daudef/simple-terminal-control
Project-URL: Bug Tracker, https://github.com/daudef/simple-terminal-control/issues
Author-email: Florian Daude <floriandaude@hotmail.fr>
License: MIT License
Classifier: License :: OSI Approved :: MIT License
Classifier: Programming Language :: Python :: 3
Requires-Python: >=3.10
